{"id":"e01444693dc58bcde9a9ce00b","tags":[],"name":"Tonker Style Release","type":"gift ability","level":"1","traits":"BALA PLOKAMI,CONCENTRATION,connected,TRANSMUTATION","actions":"f","body":"**Source** Alec Ellsworth\n-\nThe triggering target of the *Tonker Style Release* will instantly be released. The target is no longer considered Connected by the Bala Plokami. If the target took damage directly because of this ability, this ability gains the Attack trait for this use only. If the target was the only target considered Connected by Bala Plokami, Bala Plokami loses the Connected trait.","meta":{"public":0,"url":"VRYXWrwb"}}